{
  "gold_path": "training_data/goldset_v6/goldset_v6_merged.json",
  "num_records": 200,
  "num_predictions": 107,
  "mode": "pipeline",
  "raw_threshold": 0.01,
  "disable_label_min": false,
  "context_window": 0,
  "label_profile": "balanced",
  "drop_labels": [],
  "active_labels": [
    "family_member",
    "place",
    "org",
    "food_item",
    "job_role",
    "health_condition",
    "activity"
  ],
  "num_raw_predictions": 509,
  "extraction_time_s": 14.14,
  "ms_per_message": 70.7,
  "overall": {
    "precision": 0.2991,
    "recall": 0.3516,
    "f1": 0.3232,
    "tp": 32,
    "fp": 75,
    "fn": 59,
    "support": 91
  },
  "per_label": {
    "activity": {
      "precision": 0.5,
      "recall": 0.25,
      "f1": 0.3333,
      "tp": 1,
      "fp": 1,
      "fn": 3,
      "support": 4
    },
    "family_member": {
      "precision": 0.64,
      "recall": 0.8,
      "f1": 0.7111,
      "tp": 16,
      "fp": 9,
      "fn": 4,
      "support": 20
    },
    "food_item": {
      "precision": 0.1429,
      "recall": 1.0,
      "f1": 0.25,
      "tp": 5,
      "fp": 30,
      "fn": 0,
      "support": 5
    },
    "health_condition": {
      "precision": 0.0,
      "recall": 0.0,
      "f1": 0.0,
      "tp": 0,
      "fp": 1,
      "fn": 0,
      "support": 0
    },
    "job_role": {
      "precision": 0.0,
      "recall": 0.0,
      "f1": 0.0,
      "tp": 0,
      "fp": 1,
      "fn": 0,
      "support": 0
    },
    "org": {
      "precision": 0.0,
      "recall": 0.0,
      "f1": 0.0,
      "tp": 0,
      "fp": 3,
      "fn": 5,
      "support": 5
    },
    "person_name": {
      "precision": 0.0,
      "recall": 0.0,
      "f1": 0.0,
      "tp": 0,
      "fp": 0,
      "fn": 36,
      "support": 36
    },
    "place": {
      "precision": 0.25,
      "recall": 0.4762,
      "f1": 0.3279,
      "tp": 10,
      "fp": 30,
      "fn": 11,
      "support": 21
    }
  },
  "per_type": {
    "health.condition": {
      "precision": 0.0,
      "recall": 0.0,
      "f1": 0.0,
      "tp": 0,
      "fp": 1,
      "fn": 0,
      "support": 0
    },
    "location.current": {
      "precision": 0.0,
      "recall": 0.0,
      "f1": 0.0,
      "tp": 0,
      "fp": 30,
      "fn": 0,
      "support": 0
    },
    "preference.activity": {
      "precision": 0.0,
      "recall": 0.0,
      "f1": 0.0,
      "tp": 0,
      "fp": 1,
      "fn": 0,
      "support": 0
    },
    "preference.food_like": {
      "precision": 0.0,
      "recall": 0.0,
      "f1": 0.0,
      "tp": 0,
      "fp": 30,
      "fn": 0,
      "support": 0
    },
    "relationship.family": {
      "precision": 0.0,
      "recall": 0.0,
      "f1": 0.0,
      "tp": 0,
      "fp": 9,
      "fn": 0,
      "support": 0
    },
    "unknown": {
      "precision": 1.0,
      "recall": 0.3516,
      "f1": 0.5203,
      "tp": 32,
      "fp": 0,
      "fn": 59,
      "support": 91
    },
    "work.employer": {
      "precision": 0.0,
      "recall": 0.0,
      "f1": 0.0,
      "tp": 0,
      "fp": 3,
      "fn": 0,
      "support": 0
    },
    "work.job_title": {
      "precision": 0.0,
      "recall": 0.0,
      "f1": 0.0,
      "tp": 0,
      "fp": 1,
      "fn": 0,
      "support": 0
    }
  },
  "per_slice": {
    "near_miss": {
      "precision": 0.5714,
      "recall": 0.2581,
      "f1": 0.3556,
      "tp": 8,
      "fp": 6,
      "fn": 23,
      "support": 31
    },
    "positive": {
      "precision": 0.2472,
      "recall": 0.44,
      "f1": 0.3165,
      "tp": 22,
      "fp": 67,
      "fn": 28,
      "support": 50
    },
    "random": {
      "precision": 0.5,
      "recall": 0.2,
      "f1": 0.2857,
      "tp": 2,
      "fp": 2,
      "fn": 8,
      "support": 10
    }
  },
  "threshold_sweep": [
    {
      "threshold": 0.3,
      "precision": 0.2716,
      "recall": 0.4835,
      "f1": 0.3478,
      "tp": 44,
      "fp": 118,
      "fn": 47,
      "support": 91
    },
    {
      "threshold": 0.35,
      "precision": 0.277,
      "recall": 0.4505,
      "f1": 0.3431,
      "tp": 41,
      "fp": 107,
      "fn": 50,
      "support": 91
    },
    {
      "threshold": 0.4,
      "precision": 0.2889,
      "recall": 0.4286,
      "f1": 0.3451,
      "tp": 39,
      "fp": 96,
      "fn": 52,
      "support": 91
    },
    {
      "threshold": 0.45,
      "precision": 0.296,
      "recall": 0.4066,
      "f1": 0.3426,
      "tp": 37,
      "fp": 88,
      "fn": 54,
      "support": 91
    },
    {
      "threshold": 0.5,
      "precision": 0.3009,
      "recall": 0.3736,
      "f1": 0.3333,
      "tp": 34,
      "fp": 79,
      "fn": 57,
      "support": 91
    },
    {
      "threshold": 0.55,
      "precision": 0.3298,
      "recall": 0.3407,
      "f1": 0.3351,
      "tp": 31,
      "fp": 63,
      "fn": 60,
      "support": 91
    },
    {
      "threshold": 0.6,
      "precision": 0.3293,
      "recall": 0.2967,
      "f1": 0.3121,
      "tp": 27,
      "fp": 55,
      "fn": 64,
      "support": 91
    },
    {
      "threshold": 0.65,
      "precision": 0.3521,
      "recall": 0.2747,
      "f1": 0.3086,
      "tp": 25,
      "fp": 46,
      "fn": 66,
      "support": 91
    },
    {
      "threshold": 0.7,
      "precision": 0.3333,
      "recall": 0.2198,
      "f1": 0.2649,
      "tp": 20,
      "fp": 40,
      "fn": 71,
      "support": 91
    },
    {
      "threshold": 0.75,
      "precision": 0.3864,
      "recall": 0.1868,
      "f1": 0.2519,
      "tp": 17,
      "fp": 27,
      "fn": 74,
      "support": 91
    },
    {
      "threshold": 0.8,
      "precision": 0.375,
      "recall": 0.1319,
      "f1": 0.1951,
      "tp": 12,
      "fp": 20,
      "fn": 79,
      "support": 91
    }
  ],
  "error_slices": {
    "short_message_errors": 12,
    "fp_on_negatives": 0,
    "message_length_distribution": {
      "<20": 40,
      "20-50": 89,
      "50-100": 51,
      ">100": 20
    },
    "total_errors": 134
  },
  "raw_stats": {
    "raw_total_predictions": 509,
    "raw_messages_with_predictions": 193,
    "raw_messages_total": 200,
    "raw_predictions_per_message": 2.545,
    "raw_score_summary": {
      "min": 0.01,
      "p25": 0.0269,
      "p50": 0.0973,
      "p75": 0.4453,
      "p90": 0.7234,
      "p95": 0.8198,
      "max": 0.9661
    },
    "raw_top_labels": [
      {
        "label": "family_member",
        "count": 257
      },
      {
        "label": "place",
        "count": 91
      },
      {
        "label": "food_item",
        "count": 82
      },
      {
        "label": "activity",
        "count": 36
      },
      {
        "label": "org",
        "count": 25
      },
      {
        "label": "job_role",
        "count": 12
      },
      {
        "label": "health_condition",
        "count": 6
      }
    ]
  }
}